mqrdr/__init__.py
mqrdr/accounts.py
mqrdr/articles.py
mqrdr/authors.py
mqrdr/file_utils.py
mqrdr/groups.py
mqrdr/projects.py
mqrdr/settings.py
mqrdr/utils.py
tests/__init__.py
tests/test_utils.py
mqrdr-0.3.1.dist-info/METADATA
mqrdr-0.3.1.dist-info/WHEEL
mqrdr-0.3.1.dist-info/top_level.txt
mqrdr-0.3.1.dist-info/RECORD
