Metadata-Version: 2.1
Name: mqrdr
Version: 0.3.1
Summary: Python 3 library, leveraging off of the Figshare API, for programmatic interaction with the Macquarie University Research Data Repository
Home-page: https://github.com/gdevine/mqrdr
Author: Gerry Devine
Author-email: gerry.devine@mq.edu.au
License: UNKNOWN
Platform: UNKNOWN
Classifier: Programming Language :: Python :: 3
Classifier: License :: OSI Approved :: MIT License
Classifier: Operating System :: OS Independent
Requires-Python: >=3
Requires-Dist: requests
